fastfuels_core/__init__.py
fastfuels_core/base.py
fastfuels_core/disc_sampling.py
fastfuels_core/plotting.py
fastfuels_core/point_process.py
fastfuels_core/ref_data.py
fastfuels_core/treatments.py
fastfuels_core/trees.py
fastfuels_core/voxelization.py
fastfuels_core/crown_profile_models/__init__.py
fastfuels_core/crown_profile_models/abc.py
fastfuels_core/crown_profile_models/beta.py
fastfuels_core/crown_profile_models/purves.py
fastfuels_core/data/REF_JENKINS.csv
fastfuels_core/data/REF_SPECIES.csv
fastfuels_core/fuel_moisture/__init__.py
fastfuels_core/fuel_moisture/fosberg.py
fastfuels_core/onramps/__init__.py
fastfuels_core/onramps/hag_pim.py
fastfuels_core-0.6.0.dist-info/licenses/LICENSE
fastfuels_core-0.6.0.dist-info/METADATA
fastfuels_core-0.6.0.dist-info/WHEEL
fastfuels_core-0.6.0.dist-info/top_level.txt
fastfuels_core-0.6.0.dist-info/RECORD
